{
  "id": "adv_card_szk_04_02",
  "title": "兵藤雫 2話 ドルオタの名に懸けて",
  "script": [
    {
      "type": "background",
      "src": "https://apiip.dasewasia.my.id/storyBackground/env_adv_2d_lesson-01-noon.webp",
      "bgName": "env_adv_3d_lesson-02-000-night",
      "startTime": 0
    },
    {
      "type": "dialogue",
      "speakerCode": "szk",
      "speakerName": "兵藤雫",
      "speakerNameEn": "Shizuku",
      "iconUrl": "https://apiip.dasewasia.my.id/iconCharacter/chara-shizuku.png",
      "voiceUrl": "https://apiip.dasewasia.my.id/cardStoryVoice/sud_vo_adv_card_szk_04_02/sud_vo_adv_card_szk_04_02-szk001.m4a",
      "text": "という訳で、かっこ良くなるために\n今日から特訓する……！",
      "translations": {
        "en": "So‚ in order to become cooler‚\nWe're starting special training today…!",
        "id": ""
      },
      "startTime": 3.9666666667,
      "sfxList": []
    },
    {
      "type": "dialogue",
      "speakerCode": "szk",
      "speakerName": "兵藤雫",
      "speakerNameEn": "Shizuku",
      "iconUrl": "https://apiip.dasewasia.my.id/iconCharacter/chara-shizuku.png",
      "voiceUrl": "https://apiip.dasewasia.my.id/cardStoryVoice/sud_vo_adv_card_szk_04_02/sud_vo_adv_card_szk_04_02-szk002.m4a",
      "text": "……ところで、特訓って何をすればいい？",
      "translations": {
        "en": "…By the way‚ what should we do for special training?",
        "id": ""
      },
      "startTime": 6.3666666667,
      "sfxList": []
    },
    {
      "type": "dialogue",
      "speakerCode": "koh",
      "speakerName": "{user}",
      "speakerNameEn": "{user}",
      "iconUrl": "https://apiip.dasewasia.my.id/iconCharacter/chara-makino.png",
      "voiceUrl": "https://apiip.dasewasia.my.id/cardStoryVoice/sud_vo_adv_card_szk_04_02/sud_vo_adv_card_szk_04_02-koh001.m4a",
      "text": "俺に聞かれても困るが……そうだな……\nかっこいい言葉を言ってみるのはどうだ？",
      "translations": {
        "en": "It's kind of difficult for me to answer… but‚ well…\nHow about trying to say cool words?",
        "id": ""
      },
      "startTime": 14.5333333333,
      "sfxList": []
    },
    {
      "type": "dialogue",
      "speakerCode": "koh",
      "speakerName": "{user}",
      "speakerNameEn": "{user}",
      "iconUrl": "https://apiip.dasewasia.my.id/iconCharacter/chara-makino.png",
      "voiceUrl": "https://apiip.dasewasia.my.id/cardStoryVoice/sud_vo_adv_card_szk_04_02/sud_vo_adv_card_szk_04_02-koh002.m4a",
      "text": "そういうセリフを言う時は\n自然と顔つきもかっこ良くなるんじゃないか？",
      "translations": {
        "en": "When you say lines like that‚\nyour facial expression might naturally become cooler.",
        "id": ""
      },
      "startTime": 19.4333333333,
      "sfxList": []
    },
    {
      "type": "dialogue",
      "speakerCode": "szk",
      "speakerName": "兵藤雫",
      "speakerNameEn": "Shizuku",
      "iconUrl": "https://apiip.dasewasia.my.id/iconCharacter/chara-shizuku.png",
      "voiceUrl": "https://apiip.dasewasia.my.id/cardStoryVoice/sud_vo_adv_card_szk_04_02/sud_vo_adv_card_szk_04_02-szk003.m4a",
      "text": "分かった、やってみる……！",
      "translations": {
        "en": "Got it‚ I'll give it a try…!",
        "id": ""
      },
      "startTime": 22.6,
      "sfxList": []
    },
    {
      "type": "dialogue",
      "speakerCode": "szk",
      "speakerName": "兵藤雫",
      "speakerNameEn": "Shizuku",
      "iconUrl": "https://apiip.dasewasia.my.id/iconCharacter/chara-shizuku.png",
      "voiceUrl": "https://apiip.dasewasia.my.id/cardStoryVoice/sud_vo_adv_card_szk_04_02/sud_vo_adv_card_szk_04_02-szk004.m4a",
      "text": "――初めての挫折を、私達が味わわせてあげる\n……キリッ！",
      "translations": {
        "en": "――We will make you taste your first failure…\n…Sharp!",
        "id": ""
      },
      "startTime": 29.8,
      "sfxList": []
    },
    {
      "type": "dialogue",
      "speakerCode": "szk",
      "speakerName": "兵藤雫",
      "speakerNameEn": "Shizuku",
      "iconUrl": "https://apiip.dasewasia.my.id/iconCharacter/chara-shizuku.png",
      "voiceUrl": "https://apiip.dasewasia.my.id/cardStoryVoice/sud_vo_adv_card_szk_04_02/sud_vo_adv_card_szk_04_02-szk005.m4a",
      "text": "……どう、かな？",
      "translations": {
        "en": "…So‚ what do you think?",
        "id": ""
      },
      "startTime": 31.6333333333,
      "sfxList": []
    },
    {
      "type": "dialogue",
      "speakerCode": "koh",
      "speakerName": "{user}",
      "speakerNameEn": "{user}",
      "iconUrl": "https://apiip.dasewasia.my.id/iconCharacter/chara-makino.png",
      "voiceUrl": "https://apiip.dasewasia.my.id/cardStoryVoice/sud_vo_adv_card_szk_04_02/sud_vo_adv_card_szk_04_02-koh003.m4a",
      "text": "なんというか……微妙だな……\nもしかして、今のは莉央さんの真似か？",
      "translations": {
        "en": "It's kind of… subtle…\nWas that just an imitation of Rio?",
        "id": ""
      },
      "startTime": 37.0333333333,
      "sfxList": []
    },
    {
      "type": "dialogue",
      "speakerCode": "szk",
      "speakerName": "兵藤雫",
      "speakerNameEn": "Shizuku",
      "iconUrl": "https://apiip.dasewasia.my.id/iconCharacter/chara-shizuku.png",
      "voiceUrl": "https://apiip.dasewasia.my.id/cardStoryVoice/sud_vo_adv_card_szk_04_02/sud_vo_adv_card_szk_04_02-szk006.m4a",
      "text": "そう。莉央さんをイメージしてみた……\nかっこいいと言えば、リズノワだから……",
      "translations": {
        "en": "Yeah. I tried to imagine Rio…\nSince LizNoir is cool when they speak cool lines…",
        "id": ""
      },
      "startTime": 44.0333333333,
      "sfxList": []
    },
    {
      "type": "dialogue",
      "speakerCode": "koh",
      "speakerName": "{user}",
      "speakerNameEn": "{user}",
      "iconUrl": "https://apiip.dasewasia.my.id/iconCharacter/chara-makino.png",
      "voiceUrl": "https://apiip.dasewasia.my.id/cardStoryVoice/sud_vo_adv_card_szk_04_02/sud_vo_adv_card_szk_04_02-koh004.m4a",
      "text": "なるほど、アイドル好きな雫らしいな\nでもここは別の言葉にした方がいいんじゃないか？",
      "translations": {
        "en": "I see‚ that's very much like you‚ who loves idols.\nBut shouldn't you try using different words?",
        "id": ""
      },
      "startTime": 51.3,
      "sfxList": []
    },
    {
      "type": "dialogue",
      "speakerCode": "szk",
      "speakerName": "兵藤雫",
      "speakerNameEn": "Shizuku",
      "iconUrl": "https://apiip.dasewasia.my.id/iconCharacter/chara-shizuku.png",
      "voiceUrl": "https://apiip.dasewasia.my.id/cardStoryVoice/sud_vo_adv_card_szk_04_02/sud_vo_adv_card_szk_04_02-szk007.m4a",
      "text": "分かった。違う言葉にする……\nそれじゃあ……",
      "translations": {
        "en": "Got it. I'll use different words…\nThen…",
        "id": ""
      },
      "startTime": 58.8666666667,
      "sfxList": []
    },
    {
      "type": "dialogue",
      "speakerCode": "szk",
      "speakerName": "兵藤雫",
      "speakerNameEn": "Shizuku",
      "iconUrl": "https://apiip.dasewasia.my.id/iconCharacter/chara-shizuku.png",
      "voiceUrl": "https://apiip.dasewasia.my.id/cardStoryVoice/sud_vo_adv_card_szk_04_02/sud_vo_adv_card_szk_04_02-szk008.m4a",
      "text": "――僕はカニカマとずるいことは嫌いなんだ\n……キリッ！",
      "translations": {
        "en": "――I dislike crab sticks and unfair things…!\n…Sharp!",
        "id": ""
      },
      "startTime": 64.3,
      "sfxList": []
    },
    {
      "type": "dialogue",
      "speakerCode": "szk",
      "speakerName": "兵藤雫",
      "speakerNameEn": "Shizuku",
      "iconUrl": "https://apiip.dasewasia.my.id/iconCharacter/chara-shizuku.png",
      "voiceUrl": "https://apiip.dasewasia.my.id/cardStoryVoice/sud_vo_adv_card_szk_04_02/sud_vo_adv_card_szk_04_02-szk009.m4a",
      "text": "……どう、かな？",
      "translations": {
        "en": "…So‚ what do you think?",
        "id": ""
      },
      "startTime": 65.7,
      "sfxList": []
    },
    {
      "type": "dialogue",
      "speakerCode": "koh",
      "speakerName": "{user}",
      "speakerNameEn": "{user}",
      "iconUrl": "https://apiip.dasewasia.my.id/iconCharacter/chara-makino.png",
      "voiceUrl": "https://apiip.dasewasia.my.id/cardStoryVoice/sud_vo_adv_card_szk_04_02/sud_vo_adv_card_szk_04_02-koh005.m4a",
      "text": "葵の真似になっただけじゃないか\nそれに、いちいちキメ顔しないといけないのか？",
      "translations": {
        "en": "It seems like you just imitated Aoi.\nBesides‚ do you have to make a determined expression every time?",
        "id": ""
      },
      "startTime": 69.8333333333,
      "sfxList": []
    },
    {
      "type": "dialogue",
      "speakerCode": "szk",
      "speakerName": "兵藤雫",
      "speakerNameEn": "Shizuku",
      "iconUrl": "https://apiip.dasewasia.my.id/iconCharacter/chara-shizuku.png",
      "voiceUrl": "https://apiip.dasewasia.my.id/cardStoryVoice/sud_vo_adv_card_szk_04_02/sud_vo_adv_card_szk_04_02-szk010.m4a",
      "text": "これもダメ……？　難しい……",
      "translations": {
        "en": "Is this not good either…? It's tough…",
        "id": ""
      },
      "startTime": 73.2666666667,
      "sfxList": []
    },
    {
      "type": "dialogue",
      "speakerCode": "szk",
      "speakerName": "兵藤雫",
      "speakerNameEn": "Shizuku",
      "iconUrl": "https://apiip.dasewasia.my.id/iconCharacter/chara-shizuku.png",
      "voiceUrl": "https://apiip.dasewasia.my.id/cardStoryVoice/sud_vo_adv_card_szk_04_02/sud_vo_adv_card_szk_04_02-szk011.m4a",
      "text": "そもそも、かっこいいって何……？\n見た目……？　仕草……？　雰囲気……？",
      "translations": {
        "en": "Come to think of it‚ what does it mean to be cool…?\nAppearance…? Gestures…? Atmosphere…?",
        "id": ""
      },
      "startTime": 81,
      "sfxList": []
    },
    {
      "type": "dialogue",
      "speakerCode": "szk",
      "speakerName": "兵藤雫",
      "speakerNameEn": "Shizuku",
      "iconUrl": "https://apiip.dasewasia.my.id/iconCharacter/chara-shizuku.png",
      "voiceUrl": "https://apiip.dasewasia.my.id/cardStoryVoice/sud_vo_adv_card_szk_04_02/sud_vo_adv_card_szk_04_02-szk012.m4a",
      "text": "それが分からないと、特訓にならない……\nもっと勉強しないと……",
      "translations": {
        "en": "If I don't understand that‚ this won't become special training…\nI need to study more…",
        "id": ""
      },
      "startTime": 88.6,
      "sfxList": []
    },
    {
      "type": "dialogue",
      "speakerCode": "szk",
      "speakerName": "兵藤雫",
      "speakerNameEn": "Shizuku",
      "iconUrl": "https://apiip.dasewasia.my.id/iconCharacter/chara-shizuku.png",
      "voiceUrl": "https://apiip.dasewasia.my.id/cardStoryVoice/sud_vo_adv_card_szk_04_02/sud_vo_adv_card_szk_04_02-szk013.m4a",
      "text": "でも、勉強するって……一体どうしたら……\n……はっ！",
      "translations": {
        "en": "But studying… how on earth…\n…Ah!",
        "id": ""
      },
      "startTime": 96.5333333333,
      "sfxList": [
        {
          "src": "https://apiip.dasewasia.my.id/storyBgm/sud_se_adv_run-in-single-01.m4a",
          "delay": 7566.666666699987,
          "startTime": 104.1
        }
      ]
    },
    {
      "type": "dialogue",
      "speakerCode": "szk",
      "speakerName": "兵藤雫",
      "speakerNameEn": "Shizuku",
      "iconUrl": "https://apiip.dasewasia.my.id/iconCharacter/chara-shizuku.png",
      "voiceUrl": "https://apiip.dasewasia.my.id/cardStoryVoice/sud_vo_adv_card_szk_04_02/sud_vo_adv_card_szk_04_02-szk014.m4a",
      "text": "そういう人を観察して極意を学ぶ……\nうん、それがいい……ちょっと観察して来る……！",
      "translations": {
        "en": "Observe people like that and learn their secrets…\nYeah‚ that's a good idea… I'll observe a bit…!",
        "id": ""
      },
      "startTime": 101.5666666667,
      "sfxList": []
    },
    {
      "type": "dialogue",
      "speakerCode": "koh",
      "speakerName": "{user}",
      "speakerNameEn": "{user}",
      "iconUrl": "https://apiip.dasewasia.my.id/iconCharacter/chara-makino.png",
      "voiceUrl": "https://apiip.dasewasia.my.id/cardStoryVoice/sud_vo_adv_card_szk_04_02/sud_vo_adv_card_szk_04_02-koh006.m4a",
      "text": "えっ、雫！？\n……観察するって、何をするつもりだ？",
      "translations": {
        "en": "Huh‚ Shizuku!?\n…Observing‚ what exactly are you planning to do?",
        "id": ""
      },
      "startTime": 108.8666666667,
      "sfxList": []
    },
    {
      "type": "background",
      "src": "https://apiip.dasewasia.my.id/storyBackground/env_adv_2d_tokyoentrance-00-noon.webp",
      "bgName": "tokyoentrance-00-noon",
      "startTime": 113.2333333333
    },
    {
      "type": "background",
      "src": "https://apiip.dasewasia.my.id/storyBackground/env_adv_2d_tokyoentrance-00-noon.webp",
      "bgName": "tokyoentrance-00-noon",
      "startTime": 113.2333333333
    },
    {
      "type": "dialogue",
      "speakerCode": "koh",
      "speakerName": "{user}",
      "speakerNameEn": "{user}",
      "iconUrl": "https://apiip.dasewasia.my.id/iconCharacter/chara-makino.png",
      "voiceUrl": "https://apiip.dasewasia.my.id/cardStoryVoice/sud_vo_adv_card_szk_04_02/sud_vo_adv_card_szk_04_02-koh007.m4a",
      "text": "雫のやつ、どこに行ったんだ？\n……ん？　あれはスリクスか？",
      "translations": {
        "en": "Where did that Shizuku go?\n…Hm? Is that IIIX?",
        "id": ""
      },
      "startTime": 117.7,
      "sfxList": [
        {
          "src": "https://apiip.dasewasia.my.id/storyBgm/sud_se_adv_walk-in-single-02.m4a",
          "delay": 3099.9999999999945,
          "startTime": 120.8
        }
      ]
    },
    {
      "type": "background",
      "src": "https://apiip.dasewasia.my.id/storyBackground/env_adv_2d_tokyoentrance-00-noon.webp",
      "bgName": "tokyoentrance-00-noon",
      "startTime": 120.8
    },
    {
      "type": "dialogue",
      "speakerCode": "koh",
      "speakerName": "{user}",
      "speakerNameEn": "{user}",
      "iconUrl": "https://apiip.dasewasia.my.id/iconCharacter/chara-makino.png",
      "voiceUrl": "https://apiip.dasewasia.my.id/cardStoryVoice/sud_vo_adv_card_szk_04_02/sud_vo_adv_card_szk_04_02-koh008.m4a",
      "text": "これから出かけるみたいだな\nそして、三人の後ろをこそこそ歩いているのは……",
      "translations": {
        "en": "Seems like they're about to go somewhere.\nAnd the one sneaking behind the three…",
        "id": ""
      },
      "startTime": 123.3,
      "sfxList": []
    },
    {
      "type": "background",
      "src": "https://apiip.dasewasia.my.id/storyBackground/env_adv_2d_tokyoentrance-00-noon.webp",
      "bgName": "tokyoentrance-00-noon",
      "startTime": 128.2333333333
    },
    {
      "type": "dialogue",
      "speakerCode": "szk",
      "speakerName": "兵藤雫",
      "speakerNameEn": "Shizuku",
      "iconUrl": "https://apiip.dasewasia.my.id/iconCharacter/chara-shizuku.png",
      "voiceUrl": "https://apiip.dasewasia.my.id/cardStoryVoice/sud_vo_adv_card_szk_04_02/sud_vo_adv_card_szk_04_02-szk015.m4a",
      "text": "……はっ！　{user}さん……！",
      "translations": {
        "en": "…Ha! {user}-san…!",
        "id": ""
      },
      "startTime": 128.2333333333,
      "sfxList": []
    },
    {
      "type": "background",
      "src": "https://apiip.dasewasia.my.id/storyBackground/env_adv_2d_tokyoentrance-00-noon.webp",
      "bgName": "tokyoentrance-00-noon",
      "startTime": 130.4666666667
    },
    {
      "type": "dialogue",
      "speakerCode": "koh",
      "speakerName": "{user}",
      "speakerNameEn": "{user}",
      "iconUrl": "https://apiip.dasewasia.my.id/iconCharacter/chara-makino.png",
      "voiceUrl": "https://apiip.dasewasia.my.id/cardStoryVoice/sud_vo_adv_card_szk_04_02/sud_vo_adv_card_szk_04_02-koh009.m4a",
      "text": "雫？　そこで何をしているんだ？",
      "translations": {
        "en": "Shizuku? What are you doing there?",
        "id": ""
      },
      "startTime": 130.4666666667,
      "sfxList": []
    },
    {
      "type": "dialogue",
      "speakerCode": "szk",
      "speakerName": "兵藤雫",
      "speakerNameEn": "Shizuku",
      "iconUrl": "https://apiip.dasewasia.my.id/iconCharacter/chara-shizuku.png",
      "voiceUrl": "https://apiip.dasewasia.my.id/cardStoryVoice/sud_vo_adv_card_szk_04_02/sud_vo_adv_card_szk_04_02-szk016.m4a",
      "text": "今は話し掛けないで……\n尾行してるのがバレる",
      "translations": {
        "en": "Please don't talk to me right now…\nThey'll notice I'm tailing them.",
        "id": ""
      },
      "startTime": 135.9666666667,
      "sfxList": []
    },
    {
      "type": "background",
      "src": "https://apiip.dasewasia.my.id/storyBackground/env_adv_2d_tokyoentrance-00-noon.webp",
      "bgName": "tokyoentrance-00-noon",
      "startTime": 138.3666666667
    },
    {
      "type": "dialogue",
      "speakerCode": "szk",
      "speakerName": "兵藤雫",
      "speakerNameEn": "Shizuku",
      "iconUrl": "https://apiip.dasewasia.my.id/iconCharacter/chara-shizuku.png",
      "voiceUrl": "https://apiip.dasewasia.my.id/cardStoryVoice/sud_vo_adv_card_szk_04_02/sud_vo_adv_card_szk_04_02-szk017.m4a",
      "text": "私はどうしても、かっこ良さの秘訣を知りたい\nだからスリクスを観察してる……",
      "translations": {
        "en": "I really want to know the secret of being cool.\nThat's why I'm observing IIIX…",
        "id": ""
      },
      "startTime": 142.5,
      "sfxList": []
    },
    {
      "type": "dialogue",
      "speakerCode": "koh",
      "speakerName": "{user}",
      "speakerNameEn": "{user}",
      "iconUrl": "https://apiip.dasewasia.my.id/iconCharacter/chara-makino.png",
      "voiceUrl": "https://apiip.dasewasia.my.id/cardStoryVoice/sud_vo_adv_card_szk_04_02/sud_vo_adv_card_szk_04_02-koh010.m4a",
      "text": "それなら直接話を聞けばいいじゃないか",
      "translations": {
        "en": "If that's the case‚ why don't you just talk to them directly?",
        "id": ""
      },
      "startTime": 145.4,
      "sfxList": []
    },
    {
      "type": "background",
      "src": "https://apiip.dasewasia.my.id/storyBackground/env_adv_2d_tokyoentrance-00-noon.webp",
      "bgName": "tokyoentrance-00-noon",
      "startTime": 148.6666666667
    },
    {
      "type": "dialogue",
      "speakerCode": "szk",
      "speakerName": "兵藤雫",
      "speakerNameEn": "Shizuku",
      "iconUrl": "https://apiip.dasewasia.my.id/iconCharacter/chara-shizuku.png",
      "voiceUrl": "https://apiip.dasewasia.my.id/cardStoryVoice/sud_vo_adv_card_szk_04_02/sud_vo_adv_card_szk_04_02-szk018.m4a",
      "text": "無理。スリクスは憧れの存在……\n目が合っただけで緊張する……",
      "translations": {
        "en": "Impossible. IIIX is like an aspiration…\nI get nervous just from making eye contact…",
        "id": ""
      },
      "startTime": 151.8666666667,
      "sfxList": []
    },
    {
      "type": "background",
      "src": "https://apiip.dasewasia.my.id/storyBackground/env_adv_2d_tokyoentrance-00-noon.webp",
      "bgName": "tokyoentrance-00-noon",
      "startTime": 154.6666666667
    },
    {
      "type": "dialogue",
      "speakerCode": "szk",
      "speakerName": "兵藤雫",
      "speakerNameEn": "Shizuku",
      "iconUrl": "https://apiip.dasewasia.my.id/iconCharacter/chara-shizuku.png",
      "voiceUrl": "https://apiip.dasewasia.my.id/cardStoryVoice/sud_vo_adv_card_szk_04_02/sud_vo_adv_card_szk_04_02-szk019.m4a",
      "text": "だから隠れて観察してる……\n先輩の仕事を見て、技術を盗む……それがプロ……！",
      "translations": {
        "en": "That's why I'm watching from hiding…\nWatching a senpai's work and learning techniques… That's what being a pro is…!",
        "id": ""
      },
      "startTime": 157.8,
      "sfxList": []
    },
    {
      "type": "dialogue",
      "speakerCode": "koh",
      "speakerName": "{user}",
      "speakerNameEn": "{user}",
      "iconUrl": "https://apiip.dasewasia.my.id/iconCharacter/chara-makino.png",
      "voiceUrl": "https://apiip.dasewasia.my.id/cardStoryVoice/sud_vo_adv_card_szk_04_02/sud_vo_adv_card_szk_04_02-koh011.m4a",
      "text": "職人っぽいことを言っているが\n話し掛ける度胸がないだけだよな？",
      "translations": {
        "en": "You're saying things like a professional‚ but…\nIt's just that you lack the courage to talk to them‚ right?",
        "id": ""
      },
      "startTime": 164.3666666667,
      "sfxList": []
    },
    {
      "type": "background",
      "src": "https://apiip.dasewasia.my.id/storyBackground/env_adv_2d_tokyoentrance-00-noon.webp",
      "bgName": "tokyoentrance-00-noon",
      "startTime": 167.1
    },
    {
      "type": "dialogue",
      "speakerCode": "szk",
      "speakerName": "兵藤雫",
      "speakerNameEn": "Shizuku",
      "iconUrl": "https://apiip.dasewasia.my.id/iconCharacter/chara-shizuku.png",
      "voiceUrl": "https://apiip.dasewasia.my.id/cardStoryVoice/sud_vo_adv_card_szk_04_02/sud_vo_adv_card_szk_04_02-szk020.m4a",
      "text": "私は尾行中だから、もう行く……\nそれじゃ……",
      "translations": {
        "en": "I'm tailing them now‚ so I'm leaving…\nWell then…",
        "id": ""
      },
      "startTime": 170,
      "sfxList": [
        {
          "src": "https://apiip.dasewasia.my.id/storyBgm/sud_se_adv_walk-in-single-02.m4a",
          "delay": 3366.6666667000127,
          "startTime": 170.4666666667
        }
      ]
    },
    {
      "type": "background",
      "src": "https://apiip.dasewasia.my.id/storyBackground/env_adv_2d_tokyoentrance-00-noon.webp",
      "bgName": "tokyoentrance-00-noon",
      "startTime": 171.4333333333
    },
    {
      "type": "dialogue",
      "speakerCode": "koh",
      "speakerName": "{user}",
      "speakerNameEn": "{user}",
      "iconUrl": "https://apiip.dasewasia.my.id/iconCharacter/chara-makino.png",
      "voiceUrl": "https://apiip.dasewasia.my.id/cardStoryVoice/sud_vo_adv_card_szk_04_02/sud_vo_adv_card_szk_04_02-koh012.m4a",
      "text": "ちょっと待った\n実はさっき、franさんからメッセージがきたんだ",
      "translations": {
        "en": "Hold on a moment.\nActually‚ I got a message from fran-san earlier.",
        "id": ""
      },
      "startTime": 172.9,
      "sfxList": []
    },
    {
      "type": "dialogue",
      "speakerCode": "koh",
      "speakerName": "{user}",
      "speakerNameEn": "{user}",
      "iconUrl": "https://apiip.dasewasia.my.id/iconCharacter/chara-makino.png",
      "voiceUrl": "https://apiip.dasewasia.my.id/cardStoryVoice/sud_vo_adv_card_szk_04_02/sud_vo_adv_card_szk_04_02-koh013.m4a",
      "text": "「変な子にストーカー行為されてるから\nマネージャーならなんとかして」って……",
      "translations": {
        "en": "\"There's this weird kid stalking me\nand since you're their manager‚ do something about it.\"",
        "id": ""
      },
      "startTime": 178.4,
      "sfxList": []
    },
    {
      "type": "background",
      "src": "https://apiip.dasewasia.my.id/storyBackground/env_adv_2d_tokyoentrance-00-noon.webp",
      "bgName": "tokyoentrance-00-noon",
      "startTime": 181.7
    },
    {
      "type": "dialogue",
      "speakerCode": "szk",
      "speakerName": "兵藤雫",
      "speakerNameEn": "Shizuku",
      "iconUrl": "https://apiip.dasewasia.my.id/iconCharacter/chara-shizuku.png",
      "voiceUrl": "https://apiip.dasewasia.my.id/cardStoryVoice/sud_vo_adv_card_szk_04_02/sud_vo_adv_card_szk_04_02-szk021.m4a",
      "text": "えっ、尾行がバレてた？\nしかも、変な子って……",
      "translations": {
        "en": "Wait‚ my tailing was exposed?\nAnd they called me a weird kid…",
        "id": ""
      },
      "startTime": 185.0666666667,
      "sfxList": []
    },
    {
      "type": "dialogue",
      "speakerCode": "koh",
      "speakerName": "{user}",
      "speakerNameEn": "{user}",
      "iconUrl": "https://apiip.dasewasia.my.id/iconCharacter/chara-makino.png",
      "voiceUrl": "https://apiip.dasewasia.my.id/cardStoryVoice/sud_vo_adv_card_szk_04_02/sud_vo_adv_card_szk_04_02-koh014.m4a",
      "text": "とりあえず、ストーキングするのは迷惑だから\nやめるように",
      "translations": {
        "en": "For now‚ stalking is annoying‚\nso stop it.",
        "id": ""
      },
      "startTime": 190.3333333333,
      "sfxList": []
    },
    {
      "type": "background",
      "src": "https://apiip.dasewasia.my.id/storyBackground/env_adv_2d_tokyoentrance-00-noon.webp",
      "bgName": "tokyoentrance-00-noon",
      "startTime": 191.9
    },
    {
      "type": "dialogue",
      "speakerCode": "szk",
      "speakerName": "兵藤雫",
      "speakerNameEn": "Shizuku",
      "iconUrl": "https://apiip.dasewasia.my.id/iconCharacter/chara-shizuku.png",
      "voiceUrl": "https://apiip.dasewasia.my.id/cardStoryVoice/sud_vo_adv_card_szk_04_02/sud_vo_adv_card_szk_04_02-szk022.m4a",
      "text": "うぅ……分かった……\nでも、どうしよう……",
      "translations": {
        "en": "Ugh… Fine…\nBut what should I do…?",
        "id": ""
      },
      "startTime": 194.9666666667,
      "sfxList": []
    },
    {
      "type": "dialogue",
      "speakerCode": "szk",
      "speakerName": "兵藤雫",
      "speakerNameEn": "Shizuku",
      "iconUrl": "https://apiip.dasewasia.my.id/iconCharacter/chara-shizuku.png",
      "voiceUrl": "https://apiip.dasewasia.my.id/cardStoryVoice/sud_vo_adv_card_szk_04_02/sud_vo_adv_card_szk_04_02-szk023.m4a",
      "text": "かっこ良さの秘訣……分からなかった……\nこのままじゃ、今度の撮影は失敗するかも",
      "translations": {
        "en": "I couldn't figure out the secret to being cool…\nIf I stay like this‚ the upcoming shoot might fail…",
        "id": ""
      },
      "startTime": 201.3666666667,
      "sfxList": []
    },
    {
      "type": "background",
      "src": "https://apiip.dasewasia.my.id/storyBackground/env_adv_2d_tokyoentrance-00-noon.webp",
      "bgName": "tokyoentrance-00-noon",
      "startTime": 206.4333333333
    },
    {
      "type": "dialogue",
      "speakerCode": "szk",
      "speakerName": "兵藤雫",
      "speakerNameEn": "Shizuku",
      "iconUrl": "https://apiip.dasewasia.my.id/iconCharacter/chara-shizuku.png",
      "voiceUrl": "https://apiip.dasewasia.my.id/cardStoryVoice/sud_vo_adv_card_szk_04_02/sud_vo_adv_card_szk_04_02-szk024.m4a",
      "text": "きっと私だけリテイクの嵐……現場は大混乱……\nfranさんや莉央さんにも嫌われる……あわわわ",
      "translations": {
        "en": "I'll probably have retakes all over the place… Chaos on set…\nfran-san and Rio-san will dislike me too… Ahh!",
        "id": ""
      },
      "startTime": 210.0666666667,
      "sfxList": []
    },
    {
      "type": "background",
      "src": "https://apiip.dasewasia.my.id/storyBackground/env_adv_2d_tokyoentrance-00-noon.webp",
      "bgName": "tokyoentrance-00-noon",
      "startTime": 214.3333333333
    },
    {
      "type": "dialogue",
      "speakerCode": "koh",
      "speakerName": "{user}",
      "speakerNameEn": "{user}",
      "iconUrl": "https://apiip.dasewasia.my.id/iconCharacter/chara-makino.png",
      "voiceUrl": "https://apiip.dasewasia.my.id/cardStoryVoice/sud_vo_adv_card_szk_04_02/sud_vo_adv_card_szk_04_02-koh015.m4a",
      "text": "なぁ、雫。思うんだが……\n魅力っていうのは人それぞれ違うんじゃないか？",
      "translations": {
        "en": "Hey‚ Shizuku. Can I share a thought?\nDon't you think charm is different for each person?",
        "id": ""
      },
      "startTime": 217.3,
      "sfxList": []
    },
    {
      "type": "dialogue",
      "speakerCode": "koh",
      "speakerName": "{user}",
      "speakerNameEn": "{user}",
      "iconUrl": "https://apiip.dasewasia.my.id/iconCharacter/chara-makino.png",
      "voiceUrl": "https://apiip.dasewasia.my.id/cardStoryVoice/sud_vo_adv_card_szk_04_02/sud_vo_adv_card_szk_04_02-koh016.m4a",
      "text": "人を真似るんじゃなくて\n自分らしいかっこ良さを見つけるんだ",
      "translations": {
        "en": "Instead of imitating others‚\nFind your own kind of coolness.",
        "id": ""
      },
      "startTime": 222.6,
      "sfxList": []
    },
    {
      "type": "background",
      "src": "https://apiip.dasewasia.my.id/storyBackground/env_adv_2d_tokyoentrance-00-noon.webp",
      "bgName": "tokyoentrance-00-noon",
      "startTime": 225.2666666667
    },
    {
      "type": "dialogue",
      "speakerCode": "szk",
      "speakerName": "兵藤雫",
      "speakerNameEn": "Shizuku",
      "iconUrl": "https://apiip.dasewasia.my.id/iconCharacter/chara-shizuku.png",
      "voiceUrl": "https://apiip.dasewasia.my.id/cardStoryVoice/sud_vo_adv_card_szk_04_02/sud_vo_adv_card_szk_04_02-szk025.m4a",
      "text": "無理だと思う。私にかっこ良さなんてない……",
      "translations": {
        "en": "I think that's impossible. I don't have any kind of coolness…",
        "id": ""
      },
      "startTime": 225.2666666667,
      "sfxList": []
    },
    {
      "type": "dialogue",
      "speakerCode": "koh",
      "speakerName": "{user}",
      "speakerNameEn": "{user}",
      "iconUrl": "https://apiip.dasewasia.my.id/iconCharacter/chara-makino.png",
      "voiceUrl": "https://apiip.dasewasia.my.id/cardStoryVoice/sud_vo_adv_card_szk_04_02/sud_vo_adv_card_szk_04_02-koh017.m4a",
      "text": "いいや、雫は気付いていないだけだ\n雫はアイドルの魅力を見つけるのが得意だろ？",
      "translations": {
        "en": "No‚ you're just not aware of it.\nIsn't finding the charm of an idol your strength?",
        "id": ""
      },
      "startTime": 233.2333333333,
      "sfxList": []
    },
    {
      "type": "background",
      "src": "https://apiip.dasewasia.my.id/storyBackground/env_adv_2d_tokyoentrance-00-noon.webp",
      "bgName": "tokyoentrance-00-noon",
      "startTime": 236.6
    },
    {
      "type": "dialogue",
      "speakerCode": "koh",
      "speakerName": "{user}",
      "speakerNameEn": "{user}",
      "iconUrl": "https://apiip.dasewasia.my.id/iconCharacter/chara-makino.png",
      "voiceUrl": "https://apiip.dasewasia.my.id/cardStoryVoice/sud_vo_adv_card_szk_04_02/sud_vo_adv_card_szk_04_02-koh018.m4a",
      "text": "俺と一緒に、兵藤雫というアイドルの\nかっこ良さを見つけてみないか？",
      "translations": {
        "en": "How about trying to discover the coolness\nof Shizuku Hyodo ‚ the idol‚ along with me?",
        "id": ""
      },
      "startTime": 239.3666666667,
      "sfxList": []
    },
    {
      "type": "dialogue",
      "speakerCode": "szk",
      "speakerName": "兵藤雫",
      "speakerNameEn": "Shizuku",
      "iconUrl": "https://apiip.dasewasia.my.id/iconCharacter/chara-shizuku.png",
      "voiceUrl": "https://apiip.dasewasia.my.id/cardStoryVoice/sud_vo_adv_card_szk_04_02/sud_vo_adv_card_szk_04_02-szk026.m4a",
      "text": "私のかっこ良さを……見つける……？",
      "translations": {
        "en": "Discover… my own coolness…?",
        "id": ""
      },
      "startTime": 241.5666666667,
      "sfxList": []
    },
    {
      "type": "background",
      "src": "https://apiip.dasewasia.my.id/storyBackground/env_adv_2d_tokyoentrance-00-noon.webp",
      "bgName": "tokyoentrance-00-noon",
      "startTime": 246.0333333333
    },
    {
      "type": "dialogue",
      "speakerCode": "szk",
      "speakerName": "兵藤雫",
      "speakerNameEn": "Shizuku",
      "iconUrl": "https://apiip.dasewasia.my.id/iconCharacter/chara-shizuku.png",
      "voiceUrl": "https://apiip.dasewasia.my.id/cardStoryVoice/sud_vo_adv_card_szk_04_02/sud_vo_adv_card_szk_04_02-szk027.m4a",
      "text": "……うん。分かった、やってみる\n私は今まで……沢山のアイドルを分析してきた……",
      "translations": {
        "en": "…Yeah. Alright‚ I'll give it a try.\nI've analyzed so many idols up until now…",
        "id": ""
      },
      "startTime": 249.7666666667,
      "sfxList": []
    },
    {
      "type": "background",
      "src": "https://apiip.dasewasia.my.id/storyBackground/env_adv_2d_tokyoentrance-00-noon.webp",
      "bgName": "tokyoentrance-00-noon",
      "startTime": 254.4
    },
    {
      "type": "dialogue",
      "speakerCode": "szk",
      "speakerName": "兵藤雫",
      "speakerNameEn": "Shizuku",
      "iconUrl": "https://apiip.dasewasia.my.id/iconCharacter/chara-shizuku.png",
      "voiceUrl": "https://apiip.dasewasia.my.id/cardStoryVoice/sud_vo_adv_card_szk_04_02/sud_vo_adv_card_szk_04_02-szk028.m4a",
      "text": "ドルオタの名に懸けて……\nアイドル兵藤雫のかっこ良さ……見つけてみせる……！",
      "translations": {
        "en": "Swearing on the name of a doll otaku…\nI'll find the coolness of Idol Shizuku and show you!",
        "id": ""
      },
      "startTime": 256.5,
      "sfxList": []
    }
  ]
}