{
  "id": "adv_card_yu_51_01",
  "groupId": "card_yu_51",
  "name": "鈴村優",
  "background": null,
  "details": [
    {
      "id": "msg_1",
      "speaker": {
        "isPlayer": false,
        "characterId": "yu",
        "icon": "https://apiip.dasewasia.my.id/iconCharacter/chara-yu.png",
        "name": "鈴村優"
      },
      "text": "あ～～～どないしよ～～～瑠依ちゃん～～",
      "isChoice": false,
      "stamp": null,
      "image": null,
      "voiceUrl": "https://apiip.dasewasia.my.id/cardStoryVoice/adv_card_yu_51_01/sud_vo_adv_card_yu_51_01-yu001.m4a"
    },
    {
      "id": "msg_2",
      "speaker": {
        "isPlayer": false,
        "characterId": "yu",
        "icon": "https://apiip.dasewasia.my.id/iconCharacter/chara-yu.png",
        "name": "鈴村優"
      },
      "text": "間にあわん～～締め切り今日やのに～～助けて～～",
      "isChoice": false,
      "stamp": null,
      "image": null,
      "voiceUrl": "https://apiip.dasewasia.my.id/cardStoryVoice/adv_card_yu_51_01/sud_vo_adv_card_yu_51_01-yu001.m4a"
    },
    {
      "id": "msg_3",
      "speaker": {
        "isPlayer": false,
        "characterId": "rui",
        "icon": "https://apiip.dasewasia.my.id/iconCharacter/chara-rui.png",
        "name": "天動瑠依"
      },
      "text": "また同人誌？　いいわよ",
      "isChoice": false,
      "stamp": null,
      "image": null,
      "voiceUrl": "https://apiip.dasewasia.my.id/cardStoryVoice/adv_card_yu_51_01/sud_vo_adv_card_yu_51_01-yu001.m4a"
    },
    {
      "id": "msg_4",
      "speaker": {
        "isPlayer": false,
        "characterId": "rui",
        "icon": "https://apiip.dasewasia.my.id/iconCharacter/chara-rui.png",
        "name": "天動瑠依"
      },
      "text": "私が出来ることならなんでも手伝うわ",
      "isChoice": false,
      "stamp": null,
      "image": null,
      "voiceUrl": "https://apiip.dasewasia.my.id/cardStoryVoice/adv_card_yu_51_01/sud_vo_adv_card_yu_51_01-rui001.m4a"
    },
    {
      "id": "msg_5",
      "speaker": {
        "isPlayer": false,
        "characterId": "yu",
        "icon": "https://apiip.dasewasia.my.id/iconCharacter/chara-yu.png",
        "name": "鈴村優"
      },
      "text": "ちゃうちゃう。『ミラクル☆アイドルバースデー！』の",
      "isChoice": false,
      "stamp": null,
      "image": null,
      "voiceUrl": "https://apiip.dasewasia.my.id/cardStoryVoice/adv_card_yu_51_01/sud_vo_adv_card_yu_51_01-yu002.m4a"
    },
    {
      "id": "msg_6",
      "speaker": {
        "isPlayer": false,
        "characterId": "yu",
        "icon": "https://apiip.dasewasia.my.id/iconCharacter/chara-yu.png",
        "name": "鈴村優"
      },
      "text": "アンケートのことや",
      "isChoice": false,
      "stamp": null,
      "image": null,
      "voiceUrl": "https://apiip.dasewasia.my.id/cardStoryVoice/adv_card_yu_51_01/sud_vo_adv_card_yu_51_01-yu002.m4a"
    },
    {
      "id": "msg_7",
      "speaker": {
        "isPlayer": false,
        "characterId": "rui",
        "icon": "https://apiip.dasewasia.my.id/iconCharacter/chara-rui.png",
        "name": "天動瑠依"
      },
      "text": "あら、まだ白紙なの？　先週聞いた時は「やりたい",
      "isChoice": false,
      "stamp": null,
      "image": null,
      "voiceUrl": "https://apiip.dasewasia.my.id/cardStoryVoice/adv_card_yu_51_01/sud_vo_adv_card_yu_51_01-rui002.m4a"
    },
    {
      "id": "msg_8",
      "speaker": {
        "isPlayer": false,
        "characterId": "rui",
        "icon": "https://apiip.dasewasia.my.id/iconCharacter/chara-rui.png",
        "name": "天動瑠依"
      },
      "text": "ことがあり過ぎて困る～」って言ってたわよね？",
      "isChoice": false,
      "stamp": null,
      "image": null,
      "voiceUrl": "https://apiip.dasewasia.my.id/cardStoryVoice/adv_card_yu_51_01/sud_vo_adv_card_yu_51_01-rui002.m4a"
    },
    {
      "id": "msg_9",
      "speaker": {
        "isPlayer": false,
        "characterId": "yu",
        "icon": "https://apiip.dasewasia.my.id/iconCharacter/chara-yu.png",
        "name": "鈴村優"
      },
      "text": "そうやねん……やりたいことは沢山あんねん……",
      "isChoice": false,
      "stamp": null,
      "image": null,
      "voiceUrl": "https://apiip.dasewasia.my.id/cardStoryVoice/adv_card_yu_51_01/sud_vo_adv_card_yu_51_01-rui002.m4a"
    },
    {
      "id": "msg_10",
      "speaker": {
        "isPlayer": false,
        "characterId": "yu",
        "icon": "https://apiip.dasewasia.my.id/iconCharacter/chara-yu.png",
        "name": "鈴村優"
      },
      "text": "あんねん……けどな……ううっ……",
      "isChoice": false,
      "stamp": null,
      "image": null,
      "voiceUrl": "https://apiip.dasewasia.my.id/cardStoryVoice/adv_card_yu_51_01/sud_vo_adv_card_yu_51_01-yu003.m4a"
    },
    {
      "id": "msg_11",
      "speaker": {
        "isPlayer": false,
        "characterId": "yu",
        "icon": "https://apiip.dasewasia.my.id/iconCharacter/chara-yu.png",
        "name": "鈴村優"
      },
      "text": "思いつく「やりたいこと」が全部趣味というか……",
      "isChoice": false,
      "stamp": null,
      "image": null,
      "voiceUrl": "https://apiip.dasewasia.my.id/cardStoryVoice/adv_card_yu_51_01/sud_vo_adv_card_yu_51_01-yu004.m4a"
    },
    {
      "id": "msg_12",
      "speaker": {
        "isPlayer": false,
        "characterId": "yu",
        "icon": "https://apiip.dasewasia.my.id/iconCharacter/chara-yu.png",
        "name": "鈴村優"
      },
      "text": "オタク関係のことになってしまうんや！",
      "isChoice": false,
      "stamp": null,
      "image": null,
      "voiceUrl": "https://apiip.dasewasia.my.id/cardStoryVoice/adv_card_yu_51_01/sud_vo_adv_card_yu_51_01-yu004.m4a"
    },
    {
      "id": "msg_13",
      "speaker": {
        "isPlayer": false,
        "characterId": "rui",
        "icon": "https://apiip.dasewasia.my.id/iconCharacter/chara-rui.png",
        "name": "天動瑠依"
      },
      "text": "そんなの気にしなくていいじゃない。せっかくなんだし",
      "isChoice": false,
      "stamp": null,
      "image": null,
      "voiceUrl": "https://apiip.dasewasia.my.id/cardStoryVoice/adv_card_yu_51_01/sud_vo_adv_card_yu_51_01-rui003.m4a"
    },
    {
      "id": "msg_14",
      "speaker": {
        "isPlayer": false,
        "characterId": "rui",
        "icon": "https://apiip.dasewasia.my.id/iconCharacter/chara-rui.png",
        "name": "天動瑠依"
      },
      "text": "素直に優のやりたいことを書けばいいでしょ",
      "isChoice": false,
      "stamp": null,
      "image": null,
      "voiceUrl": "https://apiip.dasewasia.my.id/cardStoryVoice/adv_card_yu_51_01/sud_vo_adv_card_yu_51_01-rui003.m4a"
    },
    {
      "id": "msg_15",
      "speaker": {
        "isPlayer": false,
        "characterId": "yu",
        "icon": "https://apiip.dasewasia.my.id/iconCharacter/chara-yu.png",
        "name": "鈴村優"
      },
      "text": "そうは言ってもなぁ……あくまでこれはアイドル",
      "isChoice": false,
      "stamp": null,
      "image": null,
      "voiceUrl": "https://apiip.dasewasia.my.id/cardStoryVoice/adv_card_yu_51_01/sud_vo_adv_card_yu_51_01-yu005.m4a"
    },
    {
      "id": "msg_16",
      "speaker": {
        "isPlayer": false,
        "characterId": "yu",
        "icon": "https://apiip.dasewasia.my.id/iconCharacter/chara-yu.png",
        "name": "鈴村優"
      },
      "text": "『鈴村優』としてのバースデー企画やん？",
      "isChoice": false,
      "stamp": null,
      "image": null,
      "voiceUrl": "https://apiip.dasewasia.my.id/cardStoryVoice/adv_card_yu_51_01/sud_vo_adv_card_yu_51_01-yu005.m4a"
    },
    {
      "id": "msg_17",
      "speaker": {
        "isPlayer": false,
        "characterId": "yu",
        "icon": "https://apiip.dasewasia.my.id/iconCharacter/chara-yu.png",
        "name": "鈴村優"
      },
      "text": "オタクとしての『鈴村優』のバースデー企画では",
      "isChoice": false,
      "stamp": null,
      "image": null,
      "voiceUrl": "https://apiip.dasewasia.my.id/cardStoryVoice/adv_card_yu_51_01/sud_vo_adv_card_yu_51_01-yu005.m4a"
    },
    {
      "id": "msg_18",
      "speaker": {
        "isPlayer": false,
        "characterId": "yu",
        "icon": "https://apiip.dasewasia.my.id/iconCharacter/chara-yu.png",
        "name": "鈴村優"
      },
      "text": "ないし、公私混同は良くないかなって思うんや",
      "isChoice": false,
      "stamp": null,
      "image": null,
      "voiceUrl": "https://apiip.dasewasia.my.id/cardStoryVoice/adv_card_yu_51_01/sud_vo_adv_card_yu_51_01-yu006.m4a"
    },
    {
      "id": "msg_19",
      "speaker": {
        "isPlayer": false,
        "characterId": "rui",
        "icon": "https://apiip.dasewasia.my.id/iconCharacter/chara-rui.png",
        "name": "天動瑠依"
      },
      "text": "はあ……なんだかめんどくさいわね",
      "isChoice": false,
      "stamp": null,
      "image": null,
      "voiceUrl": "https://apiip.dasewasia.my.id/cardStoryVoice/adv_card_yu_51_01/sud_vo_adv_card_yu_51_01-rui004.m4a"
    },
    {
      "id": "msg_20",
      "speaker": {
        "isPlayer": false,
        "characterId": "rui",
        "icon": "https://apiip.dasewasia.my.id/iconCharacter/chara-rui.png",
        "name": "天動瑠依"
      },
      "text": "優ってよく分からないところで真面目だわ",
      "isChoice": false,
      "stamp": null,
      "image": null,
      "voiceUrl": "https://apiip.dasewasia.my.id/cardStoryVoice/adv_card_yu_51_01/sud_vo_adv_card_yu_51_01-rui004.m4a"
    },
    {
      "id": "msg_21",
      "speaker": {
        "isPlayer": false,
        "characterId": "yu",
        "icon": "https://apiip.dasewasia.my.id/iconCharacter/chara-yu.png",
        "name": "鈴村優"
      },
      "text": "え～？　そんなん言わんとって～な～",
      "isChoice": false,
      "stamp": null,
      "image": null,
      "voiceUrl": "https://apiip.dasewasia.my.id/cardStoryVoice/adv_card_yu_51_01/sud_vo_adv_card_yu_51_01-yu007.m4a"
    },
    {
      "id": "msg_22",
      "speaker": {
        "isPlayer": false,
        "characterId": "yu",
        "icon": "https://apiip.dasewasia.my.id/iconCharacter/chara-yu.png",
        "name": "鈴村優"
      },
      "text": "うちはいつだって真面目やで～？",
      "isChoice": false,
      "stamp": null,
      "image": null,
      "voiceUrl": "https://apiip.dasewasia.my.id/cardStoryVoice/adv_card_yu_51_01/sud_vo_adv_card_yu_51_01-yu007.m4a"
    },
    {
      "id": "msg_23",
      "speaker": {
        "isPlayer": false,
        "characterId": "rui",
        "icon": "https://apiip.dasewasia.my.id/iconCharacter/chara-rui.png",
        "name": "天動瑠依"
      },
      "text": "はいはい。うーん、ファンも優の趣味に関して寛容だし",
      "isChoice": false,
      "stamp": null,
      "image": null,
      "voiceUrl": "https://apiip.dasewasia.my.id/cardStoryVoice/adv_card_yu_51_01/sud_vo_adv_card_yu_51_01-yu007.m4a"
    },
    {
      "id": "msg_24",
      "speaker": {
        "isPlayer": false,
        "characterId": "rui",
        "icon": "https://apiip.dasewasia.my.id/iconCharacter/chara-rui.png",
        "name": "天動瑠依"
      },
      "text": "とりあえず細かいことは考えずに書き出してみれば？",
      "isChoice": false,
      "stamp": null,
      "image": null,
      "voiceUrl": "https://apiip.dasewasia.my.id/cardStoryVoice/adv_card_yu_51_01/sud_vo_adv_card_yu_51_01-rui005.m4a"
    },
    {
      "id": "msg_25",
      "speaker": {
        "isPlayer": false,
        "characterId": "yu",
        "icon": "https://apiip.dasewasia.my.id/iconCharacter/chara-yu.png",
        "name": "鈴村優"
      },
      "text": "それもそうやね。聖地巡礼、コラボカフェ、同人誌",
      "isChoice": false,
      "stamp": null,
      "image": null,
      "voiceUrl": "https://apiip.dasewasia.my.id/cardStoryVoice/adv_card_yu_51_01/sud_vo_adv_card_yu_51_01-rui005.m4a"
    },
    {
      "id": "msg_26",
      "speaker": {
        "isPlayer": false,
        "characterId": "yu",
        "icon": "https://apiip.dasewasia.my.id/iconCharacter/chara-yu.png",
        "name": "鈴村優"
      },
      "text": "即売会に行ってアニメショップでグッズも買いたい……",
      "isChoice": false,
      "stamp": null,
      "image": null,
      "voiceUrl": "https://apiip.dasewasia.my.id/cardStoryVoice/adv_card_yu_51_01/sud_vo_adv_card_yu_51_01-yu008.m4a"
    },
    {
      "id": "msg_27",
      "speaker": {
        "isPlayer": false,
        "characterId": "yu",
        "icon": "https://apiip.dasewasia.my.id/iconCharacter/chara-yu.png",
        "name": "鈴村優"
      },
      "text": "テーマパークコラボにカラオケコラボも捨てがたい……",
      "isChoice": false,
      "stamp": null,
      "image": null,
      "voiceUrl": "https://apiip.dasewasia.my.id/cardStoryVoice/adv_card_yu_51_01/sud_vo_adv_card_yu_51_01-yu009.m4a"
    },
    {
      "id": "msg_28",
      "speaker": {
        "isPlayer": false,
        "characterId": "yu",
        "icon": "https://apiip.dasewasia.my.id/iconCharacter/chara-yu.png",
        "name": "鈴村優"
      },
      "text": "コスプレもいいなぁ。ペト君の声優さんにも会って――",
      "isChoice": false,
      "stamp": null,
      "image": null,
      "voiceUrl": "https://apiip.dasewasia.my.id/cardStoryVoice/adv_card_yu_51_01/sud_vo_adv_card_yu_51_01-yu009.m4a"
    },
    {
      "id": "msg_29",
      "speaker": {
        "isPlayer": false,
        "characterId": "system",
        "icon": null,
        "name": "System"
      },
      "text": "――数十分後",
      "isChoice": false,
      "stamp": null,
      "image": null,
      "voiceUrl": null
    },
    {
      "id": "msg_30",
      "speaker": {
        "isPlayer": false,
        "characterId": "ski",
        "icon": "https://apiip.dasewasia.my.id/iconCharacter/chara-saki.png",
        "name": "白石沙季"
      },
      "text": "あら？　まだ会議室の電気がついていますね……",
      "isChoice": false,
      "stamp": null,
      "image": null,
      "voiceUrl": "https://apiip.dasewasia.my.id/cardStoryVoice/adv_card_yu_51_01/sud_vo_adv_card_yu_51_01-ski001.m4a"
    },
    {
      "id": "msg_31",
      "speaker": {
        "isPlayer": false,
        "characterId": "ski",
        "icon": "https://apiip.dasewasia.my.id/iconCharacter/chara-saki.png",
        "name": "白石沙季"
      },
      "text": "こんな時間に誰が使っているんでしょう……？",
      "isChoice": false,
      "stamp": null,
      "image": null,
      "voiceUrl": "https://apiip.dasewasia.my.id/cardStoryVoice/adv_card_yu_51_01/sud_vo_adv_card_yu_51_01-ski001.m4a"
    },
    {
      "id": "msg_32",
      "speaker": {
        "isPlayer": false,
        "characterId": "ski",
        "icon": "https://apiip.dasewasia.my.id/iconCharacter/chara-saki.png",
        "name": "白石沙季"
      },
      "text": "失礼します。そろそろ施錠する時間なのですが……",
      "isChoice": false,
      "stamp": null,
      "image": null,
      "voiceUrl": "https://apiip.dasewasia.my.id/cardStoryVoice/adv_card_yu_51_01/sud_vo_adv_card_yu_51_01-ski002.m4a"
    },
    {
      "id": "msg_33",
      "speaker": {
        "isPlayer": false,
        "characterId": "rui",
        "icon": "https://apiip.dasewasia.my.id/iconCharacter/chara-rui.png",
        "name": "天動瑠依"
      },
      "text": "さ、沙季、ちょっと助けて……！　私が何言っても",
      "isChoice": false,
      "stamp": null,
      "image": null,
      "voiceUrl": "https://apiip.dasewasia.my.id/cardStoryVoice/adv_card_yu_51_01/sud_vo_adv_card_yu_51_01-ski002.m4a"
    },
    {
      "id": "msg_34",
      "speaker": {
        "isPlayer": false,
        "characterId": "rui",
        "icon": "https://apiip.dasewasia.my.id/iconCharacter/chara-rui.png",
        "name": "天動瑠依"
      },
      "text": "聞こえてないみたいで……優の話が止まらないの！",
      "isChoice": false,
      "stamp": null,
      "image": null,
      "voiceUrl": "https://apiip.dasewasia.my.id/cardStoryVoice/adv_card_yu_51_01/sud_vo_adv_card_yu_51_01-rui006.m4a"
    },
    {
      "id": "msg_35",
      "speaker": {
        "isPlayer": false,
        "characterId": "ski",
        "icon": "https://apiip.dasewasia.my.id/iconCharacter/chara-saki.png",
        "name": "白石沙季"
      },
      "text": "優ちゃんに瑠依さん！？　二人きりの会議室で",
      "isChoice": false,
      "stamp": null,
      "image": null,
      "voiceUrl": "https://apiip.dasewasia.my.id/cardStoryVoice/adv_card_yu_51_01/sud_vo_adv_card_yu_51_01-rui006.m4a"
    },
    {
      "id": "msg_36",
      "speaker": {
        "isPlayer": false,
        "characterId": "ski",
        "icon": "https://apiip.dasewasia.my.id/iconCharacter/chara-saki.png",
        "name": "白石沙季"
      },
      "text": "そんなに体を密着させて……一体何してるんですか！？",
      "isChoice": false,
      "stamp": null,
      "image": null,
      "voiceUrl": "https://apiip.dasewasia.my.id/cardStoryVoice/adv_card_yu_51_01/sud_vo_adv_card_yu_51_01-ski003.m4a"
    },
    {
      "id": "msg_37",
      "speaker": {
        "isPlayer": false,
        "characterId": "rui",
        "icon": "https://apiip.dasewasia.my.id/iconCharacter/chara-rui.png",
        "name": "天動瑠依"
      },
      "text": "好きな漫画の話を聞いていたはずなんだけど",
      "isChoice": false,
      "stamp": null,
      "image": null,
      "voiceUrl": "https://apiip.dasewasia.my.id/cardStoryVoice/adv_card_yu_51_01/sud_vo_adv_card_yu_51_01-ski003.m4a"
    },
    {
      "id": "msg_38",
      "speaker": {
        "isPlayer": false,
        "characterId": "rui",
        "icon": "https://apiip.dasewasia.my.id/iconCharacter/chara-rui.png",
        "name": "天動瑠依"
      },
      "text": "どんどん優が盛り上がってきちゃって……",
      "isChoice": false,
      "stamp": null,
      "image": null,
      "voiceUrl": "https://apiip.dasewasia.my.id/cardStoryVoice/adv_card_yu_51_01/sud_vo_adv_card_yu_51_01-rui007.m4a"
    },
    {
      "id": "msg_39",
      "speaker": {
        "isPlayer": false,
        "characterId": "yu",
        "icon": "https://apiip.dasewasia.my.id/iconCharacter/chara-yu.png",
        "name": "鈴村優"
      },
      "text": "瑠依ちゃん、見て見て！　こっちがうちの最推し",
      "isChoice": false,
      "stamp": null,
      "image": null,
      "voiceUrl": "https://apiip.dasewasia.my.id/cardStoryVoice/adv_card_yu_51_01/sud_vo_adv_card_yu_51_01-rui007.m4a"
    },
    {
      "id": "msg_40",
      "speaker": {
        "isPlayer": false,
        "characterId": "yu",
        "icon": "https://apiip.dasewasia.my.id/iconCharacter/chara-yu.png",
        "name": "鈴村優"
      },
      "text": "ペト君です！　あ～この糸目がほんまに良くない！？",
      "isChoice": false,
      "stamp": null,
      "image": null,
      "voiceUrl": "https://apiip.dasewasia.my.id/cardStoryVoice/adv_card_yu_51_01/sud_vo_adv_card_yu_51_01-yu010.m4a"
    },
    {
      "id": "msg_41",
      "speaker": {
        "isPlayer": false,
        "characterId": "yu",
        "icon": "https://apiip.dasewasia.my.id/iconCharacter/chara-yu.png",
        "name": "鈴村優"
      },
      "text": "今まで一回も開眼したことなかってんけどな",
      "isChoice": false,
      "stamp": null,
      "image": null,
      "voiceUrl": "https://apiip.dasewasia.my.id/cardStoryVoice/adv_card_yu_51_01/sud_vo_adv_card_yu_51_01-yu011.m4a"
    },
    {
      "id": "msg_42",
      "speaker": {
        "isPlayer": false,
        "characterId": "yu",
        "icon": "https://apiip.dasewasia.my.id/iconCharacter/chara-yu.png",
        "name": "鈴村優"
      },
      "text": "なんと今週、満を持してペト君が開眼したんよ！",
      "isChoice": false,
      "stamp": null,
      "image": null,
      "voiceUrl": "https://apiip.dasewasia.my.id/cardStoryVoice/adv_card_yu_51_01/sud_vo_adv_card_yu_51_01-yu011.m4a"
    },
    {
      "id": "msg_43",
      "speaker": {
        "isPlayer": false,
        "characterId": "yu",
        "icon": "https://apiip.dasewasia.my.id/iconCharacter/chara-yu.png",
        "name": "鈴村優"
      },
      "text": "あ～今週の更新分、ほんまに胸アツ展開やったな～",
      "isChoice": false,
      "stamp": null,
      "image": null,
      "voiceUrl": "https://apiip.dasewasia.my.id/cardStoryVoice/adv_card_yu_51_01/sud_vo_adv_card_yu_51_01-yu012.m4a"
    },
    {
      "id": "msg_44",
      "speaker": {
        "isPlayer": false,
        "characterId": "yu",
        "icon": "https://apiip.dasewasia.my.id/iconCharacter/chara-yu.png",
        "name": "鈴村優"
      },
      "text": "あかん、思い出しただけで心拍数上がってきたわ",
      "isChoice": false,
      "stamp": null,
      "image": null,
      "voiceUrl": "https://apiip.dasewasia.my.id/cardStoryVoice/adv_card_yu_51_01/sud_vo_adv_card_yu_51_01-yu012.m4a"
    },
    {
      "id": "msg_45",
      "speaker": {
        "isPlayer": false,
        "characterId": "rui",
        "icon": "https://apiip.dasewasia.my.id/iconCharacter/chara-rui.png",
        "name": "天動瑠依"
      },
      "text": "わ、分かったから、とりあえず落ち着いて！",
      "isChoice": false,
      "stamp": null,
      "image": null,
      "voiceUrl": "https://apiip.dasewasia.my.id/cardStoryVoice/adv_card_yu_51_01/sud_vo_adv_card_yu_51_01-rui008.m4a"
    },
    {
      "id": "msg_46",
      "speaker": {
        "isPlayer": false,
        "characterId": "rui",
        "icon": "https://apiip.dasewasia.my.id/iconCharacter/chara-rui.png",
        "name": "天動瑠依"
      },
      "text": "はぁ、何言ってるのか早口過ぎて聞き取れないわ……",
      "isChoice": false,
      "stamp": null,
      "image": null,
      "voiceUrl": "https://apiip.dasewasia.my.id/cardStoryVoice/adv_card_yu_51_01/sud_vo_adv_card_yu_51_01-rui008.m4a"
    },
    {
      "id": "msg_47",
      "speaker": {
        "isPlayer": false,
        "characterId": "ski",
        "icon": "https://apiip.dasewasia.my.id/iconCharacter/chara-saki.png",
        "name": "白石沙季"
      },
      "text": "あの……もしかして優ちゃんがしてるのって",
      "isChoice": false,
      "stamp": null,
      "image": null,
      "voiceUrl": "https://apiip.dasewasia.my.id/cardStoryVoice/adv_card_yu_51_01/sud_vo_adv_card_yu_51_01-rui008.m4a"
    },
    {
      "id": "msg_48",
      "speaker": {
        "isPlayer": false,
        "characterId": "ski",
        "icon": "https://apiip.dasewasia.my.id/iconCharacter/chara-saki.png",
        "name": "白石沙季"
      },
      "text": "『問題はバケモンじゃないもん』の話ですか？",
      "isChoice": false,
      "stamp": null,
      "image": null,
      "voiceUrl": "https://apiip.dasewasia.my.id/cardStoryVoice/adv_card_yu_51_01/sud_vo_adv_card_yu_51_01-ski004.m4a"
    },
    {
      "id": "msg_49",
      "speaker": {
        "isPlayer": false,
        "characterId": "yu",
        "icon": "https://apiip.dasewasia.my.id/iconCharacter/chara-yu.png",
        "name": "鈴村優"
      },
      "text": "沙季ちゃん！？　『もんバケ』を知ってるん！？",
      "isChoice": false,
      "stamp": null,
      "image": null,
      "voiceUrl": "https://apiip.dasewasia.my.id/cardStoryVoice/adv_card_yu_51_01/sud_vo_adv_card_yu_51_01-yu013.m4a"
    },
    {
      "id": "msg_50",
      "speaker": {
        "isPlayer": false,
        "characterId": "ski",
        "icon": "https://apiip.dasewasia.my.id/iconCharacter/chara-saki.png",
        "name": "白石沙季"
      },
      "text": "『週刊ラッキー』で連載されている漫画作品ですよね？",
      "isChoice": false,
      "stamp": null,
      "image": null,
      "voiceUrl": "https://apiip.dasewasia.my.id/cardStoryVoice/adv_card_yu_51_01/sud_vo_adv_card_yu_51_01-ski005.m4a"
    },
    {
      "id": "msg_51",
      "speaker": {
        "isPlayer": false,
        "characterId": "ski",
        "icon": "https://apiip.dasewasia.my.id/iconCharacter/chara-saki.png",
        "name": "白石沙季"
      },
      "text": "私の好きな小説家さんもハマっているらしくて",
      "isChoice": false,
      "stamp": null,
      "image": null,
      "voiceUrl": "https://apiip.dasewasia.my.id/cardStoryVoice/adv_card_yu_51_01/sud_vo_adv_card_yu_51_01-ski005.m4a"
    },
    {
      "id": "msg_52",
      "speaker": {
        "isPlayer": false,
        "characterId": "ski",
        "icon": "https://apiip.dasewasia.my.id/iconCharacter/chara-saki.png",
        "name": "白石沙季"
      },
      "text": "最近アニメ化もしたとかで、人気ですよね",
      "isChoice": false,
      "stamp": null,
      "image": null,
      "voiceUrl": "https://apiip.dasewasia.my.id/cardStoryVoice/adv_card_yu_51_01/sud_vo_adv_card_yu_51_01-ski006.m4a"
    },
    {
      "id": "msg_53",
      "speaker": {
        "isPlayer": false,
        "characterId": "ski",
        "icon": "https://apiip.dasewasia.my.id/iconCharacter/chara-saki.png",
        "name": "白石沙季"
      },
      "text": "読んだことはないですが、少し気になってたんです",
      "isChoice": false,
      "stamp": null,
      "image": null,
      "voiceUrl": "https://apiip.dasewasia.my.id/cardStoryVoice/adv_card_yu_51_01/sud_vo_adv_card_yu_51_01-ski006.m4a"
    },
    {
      "id": "msg_54",
      "speaker": {
        "isPlayer": false,
        "characterId": "yu",
        "icon": "https://apiip.dasewasia.my.id/iconCharacter/chara-yu.png",
        "name": "鈴村優"
      },
      "text": "気に……なって……た……？",
      "isChoice": false,
      "stamp": null,
      "image": null,
      "voiceUrl": "https://apiip.dasewasia.my.id/cardStoryVoice/adv_card_yu_51_01/sud_vo_adv_card_yu_51_01-yu014.m4a"
    },
    {
      "id": "msg_55",
      "speaker": {
        "isPlayer": false,
        "characterId": "ski",
        "icon": "https://apiip.dasewasia.my.id/iconCharacter/chara-saki.png",
        "name": "白石沙季"
      },
      "text": "は、はい……あの、優ちゃん？　なんか目が怖いですし",
      "isChoice": false,
      "stamp": null,
      "image": null,
      "voiceUrl": "https://apiip.dasewasia.my.id/cardStoryVoice/adv_card_yu_51_01/sud_vo_adv_card_yu_51_01-ski007.m4a"
    },
    {
      "id": "msg_56",
      "speaker": {
        "isPlayer": false,
        "characterId": "ski",
        "icon": "https://apiip.dasewasia.my.id/iconCharacter/chara-saki.png",
        "name": "白石沙季"
      },
      "text": "そんなに強く手を握られると痛いのですが……",
      "isChoice": false,
      "stamp": null,
      "image": null,
      "voiceUrl": "https://apiip.dasewasia.my.id/cardStoryVoice/adv_card_yu_51_01/sud_vo_adv_card_yu_51_01-ski007.m4a"
    },
    {
      "id": "msg_57",
      "speaker": {
        "isPlayer": false,
        "characterId": "yu",
        "icon": "https://apiip.dasewasia.my.id/iconCharacter/chara-yu.png",
        "name": "鈴村優"
      },
      "text": "沙季ちゃんとりあえず漫画全巻貸すんで",
      "isChoice": false,
      "stamp": null,
      "image": null,
      "voiceUrl": "https://apiip.dasewasia.my.id/cardStoryVoice/adv_card_yu_51_01/sud_vo_adv_card_yu_51_01-ski007.m4a"
    },
    {
      "id": "msg_58",
      "speaker": {
        "isPlayer": false,
        "characterId": "yu",
        "icon": "https://apiip.dasewasia.my.id/iconCharacter/chara-yu.png",
        "name": "鈴村優"
      },
      "text": "今からうちの部屋に来てくれへん？",
      "isChoice": false,
      "stamp": null,
      "image": null,
      "voiceUrl": "https://apiip.dasewasia.my.id/cardStoryVoice/adv_card_yu_51_01/sud_vo_adv_card_yu_51_01-yu015.m4a"
    },
    {
      "id": "msg_59",
      "speaker": {
        "isPlayer": false,
        "characterId": "ski",
        "icon": "https://apiip.dasewasia.my.id/iconCharacter/chara-saki.png",
        "name": "白石沙季"
      },
      "text": "ぜひお借りしたいですけど、ゆ、優ちゃん……",
      "isChoice": false,
      "stamp": null,
      "image": null,
      "voiceUrl": "https://apiip.dasewasia.my.id/cardStoryVoice/adv_card_yu_51_01/sud_vo_adv_card_yu_51_01-yu015.m4a"
    },
    {
      "id": "msg_60",
      "speaker": {
        "isPlayer": false,
        "characterId": "ski",
        "icon": "https://apiip.dasewasia.my.id/iconCharacter/chara-saki.png",
        "name": "白石沙季"
      },
      "text": "そんなに強く腕を引っ張らないで下さい～",
      "isChoice": false,
      "stamp": null,
      "image": null,
      "voiceUrl": "https://apiip.dasewasia.my.id/cardStoryVoice/adv_card_yu_51_01/sud_vo_adv_card_yu_51_01-ski008.m4a"
    },
    {
      "id": "msg_61",
      "speaker": {
        "isPlayer": false,
        "characterId": "rui",
        "icon": "https://apiip.dasewasia.my.id/iconCharacter/chara-rui.png",
        "name": "天動瑠依"
      },
      "text": "ちょっと優！　アンケートはどうするのよ！",
      "isChoice": false,
      "stamp": null,
      "image": null,
      "voiceUrl": "https://apiip.dasewasia.my.id/cardStoryVoice/adv_card_yu_51_01/sud_vo_adv_card_yu_51_01-ski008.m4a"
    },
    {
      "id": "msg_62",
      "speaker": {
        "isPlayer": false,
        "characterId": "rui",
        "icon": "https://apiip.dasewasia.my.id/iconCharacter/chara-rui.png",
        "name": "天動瑠依"
      },
      "text": "あ……行っちゃったわ……",
      "isChoice": false,
      "stamp": null,
      "image": null,
      "voiceUrl": "https://apiip.dasewasia.my.id/cardStoryVoice/adv_card_yu_51_01/sud_vo_adv_card_yu_51_01-rui009.m4a"
    },
    {
      "id": "msg_63",
      "speaker": {
        "isPlayer": false,
        "characterId": "yu",
        "icon": "https://apiip.dasewasia.my.id/iconCharacter/chara-yu.png",
        "name": "鈴村優"
      },
      "text": "沙季ちゃんはほんまに運がええなぁ",
      "isChoice": false,
      "stamp": null,
      "image": null,
      "voiceUrl": "https://apiip.dasewasia.my.id/cardStoryVoice/adv_card_yu_51_01/sud_vo_adv_card_yu_51_01-yu016.m4a"
    },
    {
      "id": "msg_64",
      "speaker": {
        "isPlayer": false,
        "characterId": "yu",
        "icon": "https://apiip.dasewasia.my.id/iconCharacter/chara-yu.png",
        "name": "鈴村優"
      },
      "text": "『もんバケ』を履修するなら今がベストタイミング！",
      "isChoice": false,
      "stamp": null,
      "image": null,
      "voiceUrl": "https://apiip.dasewasia.my.id/cardStoryVoice/adv_card_yu_51_01/sud_vo_adv_card_yu_51_01-yu016.m4a"
    },
    {
      "id": "msg_65",
      "speaker": {
        "isPlayer": false,
        "characterId": "ski",
        "icon": "https://apiip.dasewasia.my.id/iconCharacter/chara-saki.png",
        "name": "白石沙季"
      },
      "text": "はあ……そうなんですか",
      "isChoice": false,
      "stamp": null,
      "image": null,
      "voiceUrl": "https://apiip.dasewasia.my.id/cardStoryVoice/adv_card_yu_51_01/sud_vo_adv_card_yu_51_01-ski009.m4a"
    },
    {
      "id": "msg_66",
      "speaker": {
        "isPlayer": false,
        "characterId": "yu",
        "icon": "https://apiip.dasewasia.my.id/iconCharacter/chara-yu.png",
        "name": "鈴村優"
      },
      "text": "一月から始まったアニメは今期の覇権と言われる",
      "isChoice": false,
      "stamp": null,
      "image": null,
      "voiceUrl": "https://apiip.dasewasia.my.id/cardStoryVoice/adv_card_yu_51_01/sud_vo_adv_card_yu_51_01-yu017.m4a"
    },
    {
      "id": "msg_67",
      "speaker": {
        "isPlayer": false,
        "characterId": "yu",
        "icon": "https://apiip.dasewasia.my.id/iconCharacter/chara-yu.png",
        "name": "鈴村優"
      },
      "text": "ほど一世を風靡しているんです",
      "isChoice": false,
      "stamp": null,
      "image": null,
      "voiceUrl": "https://apiip.dasewasia.my.id/cardStoryVoice/adv_card_yu_51_01/sud_vo_adv_card_yu_51_01-yu017.m4a"
    },
    {
      "id": "msg_68",
      "speaker": {
        "isPlayer": false,
        "characterId": "yu",
        "icon": "https://apiip.dasewasia.my.id/iconCharacter/chara-yu.png",
        "name": "鈴村優"
      },
      "text": "内容がいいのはもちろんなんやけど、作画がほんまに",
      "isChoice": false,
      "stamp": null,
      "image": null,
      "voiceUrl": "https://apiip.dasewasia.my.id/cardStoryVoice/adv_card_yu_51_01/sud_vo_adv_card_yu_51_01-yu018.m4a"
    },
    {
      "id": "msg_69",
      "speaker": {
        "isPlayer": false,
        "characterId": "yu",
        "icon": "https://apiip.dasewasia.my.id/iconCharacter/chara-yu.png",
        "name": "鈴村優"
      },
      "text": "凄くて……毎週劇場版のクオリティやねん……",
      "isChoice": false,
      "stamp": null,
      "image": null,
      "voiceUrl": "https://apiip.dasewasia.my.id/cardStoryVoice/adv_card_yu_51_01/sud_vo_adv_card_yu_51_01-yu018.m4a"
    },
    {
      "id": "msg_70",
      "speaker": {
        "isPlayer": false,
        "characterId": "yu",
        "icon": "https://apiip.dasewasia.my.id/iconCharacter/chara-yu.png",
        "name": "鈴村優"
      },
      "text": "二か月経った今も毎回神回を更新し続けてて",
      "isChoice": false,
      "stamp": null,
      "image": null,
      "voiceUrl": "https://apiip.dasewasia.my.id/cardStoryVoice/adv_card_yu_51_01/sud_vo_adv_card_yu_51_01-yu019.m4a"
    },
    {
      "id": "msg_71",
      "speaker": {
        "isPlayer": false,
        "characterId": "yu",
        "icon": "https://apiip.dasewasia.my.id/iconCharacter/chara-yu.png",
        "name": "鈴村優"
      },
      "text": "バケモンみたいな画力でうちらを殴ってくるんです……",
      "isChoice": false,
      "stamp": null,
      "image": null,
      "voiceUrl": "https://apiip.dasewasia.my.id/cardStoryVoice/adv_card_yu_51_01/sud_vo_adv_card_yu_51_01-yu019.m4a"
    },
    {
      "id": "msg_72",
      "speaker": {
        "isPlayer": false,
        "characterId": "ski",
        "icon": "https://apiip.dasewasia.my.id/iconCharacter/chara-saki.png",
        "name": "白石沙季"
      },
      "text": "それは凄いですね……あの……すみません",
      "isChoice": false,
      "stamp": null,
      "image": null,
      "voiceUrl": "https://apiip.dasewasia.my.id/cardStoryVoice/adv_card_yu_51_01/sud_vo_adv_card_yu_51_01-ski010.m4a"
    },
    {
      "id": "msg_73",
      "speaker": {
        "isPlayer": false,
        "characterId": "ski",
        "icon": "https://apiip.dasewasia.my.id/iconCharacter/chara-saki.png",
        "name": "白石沙季"
      },
      "text": "そもそも『もんバケ』ってどんなお話なんですか？",
      "isChoice": false,
      "stamp": null,
      "image": null,
      "voiceUrl": "https://apiip.dasewasia.my.id/cardStoryVoice/adv_card_yu_51_01/sud_vo_adv_card_yu_51_01-ski010.m4a"
    },
    {
      "id": "msg_74",
      "speaker": {
        "isPlayer": false,
        "characterId": "yu",
        "icon": "https://apiip.dasewasia.my.id/iconCharacter/chara-yu.png",
        "name": "鈴村優"
      },
      "text": "語り出すと長くなるんやけど……ざっくり言うと",
      "isChoice": false,
      "stamp": null,
      "image": null,
      "voiceUrl": "https://apiip.dasewasia.my.id/cardStoryVoice/adv_card_yu_51_01/sud_vo_adv_card_yu_51_01-yu020.m4a"
    },
    {
      "id": "msg_75",
      "speaker": {
        "isPlayer": false,
        "characterId": "yu",
        "icon": "https://apiip.dasewasia.my.id/iconCharacter/chara-yu.png",
        "name": "鈴村優"
      },
      "text": "人間社会に紛れてるモンスターを倒すバトルものやな",
      "isChoice": false,
      "stamp": null,
      "image": null,
      "voiceUrl": "https://apiip.dasewasia.my.id/cardStoryVoice/adv_card_yu_51_01/sud_vo_adv_card_yu_51_01-yu020.m4a"
    },
    {
      "id": "msg_76",
      "speaker": {
        "isPlayer": false,
        "characterId": "yu",
        "icon": "https://apiip.dasewasia.my.id/iconCharacter/chara-yu.png",
        "name": "鈴村優"
      },
      "text": "でもただのバトルものちゃうねん！　その戦いの",
      "isChoice": false,
      "stamp": null,
      "image": null,
      "voiceUrl": "https://apiip.dasewasia.my.id/cardStoryVoice/adv_card_yu_51_01/sud_vo_adv_card_yu_51_01-yu021.m4a"
    },
    {
      "id": "msg_77",
      "speaker": {
        "isPlayer": false,
        "characterId": "yu",
        "icon": "https://apiip.dasewasia.my.id/iconCharacter/chara-yu.png",
        "name": "鈴村優"
      },
      "text": "裏にある人間関係とか複雑な感情とかも魅力的でな……",
      "isChoice": false,
      "stamp": null,
      "image": null,
      "voiceUrl": "https://apiip.dasewasia.my.id/cardStoryVoice/adv_card_yu_51_01/sud_vo_adv_card_yu_51_01-yu021.m4a"
    },
    {
      "id": "msg_78",
      "speaker": {
        "isPlayer": false,
        "characterId": "ski",
        "icon": "https://apiip.dasewasia.my.id/iconCharacter/chara-saki.png",
        "name": "白石沙季"
      },
      "text": "なるほど。面白そうですね。私も心情描写が",
      "isChoice": false,
      "stamp": null,
      "image": null,
      "voiceUrl": "https://apiip.dasewasia.my.id/cardStoryVoice/adv_card_yu_51_01/sud_vo_adv_card_yu_51_01-yu021.m4a"
    },
    {
      "id": "msg_79",
      "speaker": {
        "isPlayer": false,
        "characterId": "ski",
        "icon": "https://apiip.dasewasia.my.id/iconCharacter/chara-saki.png",
        "name": "白石沙季"
      },
      "text": "丁寧に書かれた小説が好きなんです",
      "isChoice": false,
      "stamp": null,
      "image": null,
      "voiceUrl": "https://apiip.dasewasia.my.id/cardStoryVoice/adv_card_yu_51_01/sud_vo_adv_card_yu_51_01-ski011.m4a"
    },
    {
      "id": "msg_80",
      "speaker": {
        "isPlayer": false,
        "characterId": "yu",
        "icon": "https://apiip.dasewasia.my.id/iconCharacter/chara-yu.png",
        "name": "鈴村優"
      },
      "text": "せやろ？　よいしょっと。これが単行本1～27巻です",
      "isChoice": false,
      "stamp": null,
      "image": null,
      "voiceUrl": "https://apiip.dasewasia.my.id/cardStoryVoice/adv_card_yu_51_01/sud_vo_adv_card_yu_51_01-yu022.m4a"
    },
    {
      "id": "msg_81",
      "speaker": {
        "isPlayer": false,
        "characterId": "yu",
        "icon": "https://apiip.dasewasia.my.id/iconCharacter/chara-yu.png",
        "name": "鈴村優"
      },
      "text": "アニメは4話まで放送されてるねんけど、録画見ます？",
      "isChoice": false,
      "stamp": null,
      "image": null,
      "voiceUrl": "https://apiip.dasewasia.my.id/cardStoryVoice/adv_card_yu_51_01/sud_vo_adv_card_yu_51_01-yu022.m4a"
    },
    {
      "id": "msg_82",
      "speaker": {
        "isPlayer": false,
        "characterId": "ski",
        "icon": "https://apiip.dasewasia.my.id/iconCharacter/chara-saki.png",
        "name": "白石沙季"
      },
      "text": "うーん、そうですね……初心者はアニメと漫画",
      "isChoice": false,
      "stamp": null,
      "image": null,
      "voiceUrl": "https://apiip.dasewasia.my.id/cardStoryVoice/adv_card_yu_51_01/sud_vo_adv_card_yu_51_01-ski012.m4a"
    },
    {
      "id": "msg_83",
      "speaker": {
        "isPlayer": false,
        "characterId": "ski",
        "icon": "https://apiip.dasewasia.my.id/iconCharacter/chara-saki.png",
        "name": "白石沙季"
      },
      "text": "どちらから入ればいいんでしょうか？",
      "isChoice": false,
      "stamp": null,
      "image": null,
      "voiceUrl": "https://apiip.dasewasia.my.id/cardStoryVoice/adv_card_yu_51_01/sud_vo_adv_card_yu_51_01-ski012.m4a"
    },
    {
      "id": "msg_84",
      "speaker": {
        "isPlayer": false,
        "characterId": "yu",
        "icon": "https://apiip.dasewasia.my.id/iconCharacter/chara-yu.png",
        "name": "鈴村優"
      },
      "text": "いい質問やね。うち的には原作から読んでほしいけど",
      "isChoice": false,
      "stamp": null,
      "image": null,
      "voiceUrl": "https://apiip.dasewasia.my.id/cardStoryVoice/adv_card_yu_51_01/sud_vo_adv_card_yu_51_01-yu023.m4a"
    },
    {
      "id": "msg_85",
      "speaker": {
        "isPlayer": false,
        "characterId": "yu",
        "icon": "https://apiip.dasewasia.my.id/iconCharacter/chara-yu.png",
        "name": "鈴村優"
      },
      "text": "アニメから入った方がハマりやすいと思うよ",
      "isChoice": false,
      "stamp": null,
      "image": null,
      "voiceUrl": "https://apiip.dasewasia.my.id/cardStoryVoice/adv_card_yu_51_01/sud_vo_adv_card_yu_51_01-yu023.m4a"
    },
    {
      "id": "msg_86",
      "speaker": {
        "isPlayer": false,
        "characterId": "ski",
        "icon": "https://apiip.dasewasia.my.id/iconCharacter/chara-saki.png",
        "name": "白石沙季"
      },
      "text": "ふむふむ",
      "isChoice": false,
      "stamp": null,
      "image": null,
      "voiceUrl": "https://apiip.dasewasia.my.id/cardStoryVoice/adv_card_yu_51_01/sud_vo_adv_card_yu_51_01-ski013.m4a"
    },
    {
      "id": "msg_87",
      "speaker": {
        "isPlayer": false,
        "characterId": "ski",
        "icon": "https://apiip.dasewasia.my.id/iconCharacter/chara-saki.png",
        "name": "白石沙季"
      },
      "text": "それじゃあアニメを見てその後漫画の方に――",
      "isChoice": false,
      "stamp": null,
      "image": null,
      "voiceUrl": "https://apiip.dasewasia.my.id/cardStoryVoice/adv_card_yu_51_01/sud_vo_adv_card_yu_51_01-ski013.m4a"
    },
    {
      "id": "msg_88",
      "speaker": {
        "isPlayer": false,
        "characterId": "rui",
        "icon": "https://apiip.dasewasia.my.id/iconCharacter/chara-rui.png",
        "name": "天動瑠依"
      },
      "text": "そこまでよ！　優、盛り上がってるところ悪いけど",
      "isChoice": false,
      "stamp": null,
      "image": null,
      "voiceUrl": "https://apiip.dasewasia.my.id/cardStoryVoice/adv_card_yu_51_01/sud_vo_adv_card_yu_51_01-ski013.m4a"
    },
    {
      "id": "msg_89",
      "speaker": {
        "isPlayer": false,
        "characterId": "rui",
        "icon": "https://apiip.dasewasia.my.id/iconCharacter/chara-rui.png",
        "name": "天動瑠依"
      },
      "text": "アンケートを書きなさい。スタッフさんが困るでしょ",
      "isChoice": false,
      "stamp": null,
      "image": null,
      "voiceUrl": "https://apiip.dasewasia.my.id/cardStoryVoice/adv_card_yu_51_01/sud_vo_adv_card_yu_51_01-rui010.m4a"
    },
    {
      "id": "msg_90",
      "speaker": {
        "isPlayer": false,
        "characterId": "yu",
        "icon": "https://apiip.dasewasia.my.id/iconCharacter/chara-yu.png",
        "name": "鈴村優"
      },
      "text": "はっ！？　ごめんな。つい、楽しくなってしまって……",
      "isChoice": false,
      "stamp": null,
      "image": null,
      "voiceUrl": "https://apiip.dasewasia.my.id/cardStoryVoice/adv_card_yu_51_01/sud_vo_adv_card_yu_51_01-yu024.m4a"
    },
    {
      "id": "msg_91",
      "speaker": {
        "isPlayer": false,
        "characterId": "yu",
        "icon": "https://apiip.dasewasia.my.id/iconCharacter/chara-yu.png",
        "name": "鈴村優"
      },
      "text": "でも、うち決めました。誕生日企画にやりたいこと！",
      "isChoice": false,
      "stamp": null,
      "image": null,
      "voiceUrl": "https://apiip.dasewasia.my.id/cardStoryVoice/adv_card_yu_51_01/sud_vo_adv_card_yu_51_01-yu024.m4a"
    },
    {
      "id": "msg_92",
      "speaker": {
        "isPlayer": false,
        "characterId": "yu",
        "icon": "https://apiip.dasewasia.my.id/iconCharacter/chara-yu.png",
        "name": "鈴村優"
      },
      "text": "さっき瑠依ちゃん「やりたいことをやればいい」って",
      "isChoice": false,
      "stamp": null,
      "image": null,
      "voiceUrl": "https://apiip.dasewasia.my.id/cardStoryVoice/adv_card_yu_51_01/sud_vo_adv_card_yu_51_01-yu025.m4a"
    },
    {
      "id": "msg_93",
      "speaker": {
        "isPlayer": false,
        "characterId": "yu",
        "icon": "https://apiip.dasewasia.my.id/iconCharacter/chara-yu.png",
        "name": "鈴村優"
      },
      "text": "うちに言ってくれたよな？",
      "isChoice": false,
      "stamp": null,
      "image": null,
      "voiceUrl": "https://apiip.dasewasia.my.id/cardStoryVoice/adv_card_yu_51_01/sud_vo_adv_card_yu_51_01-yu025.m4a"
    },
    {
      "id": "msg_94",
      "speaker": {
        "isPlayer": false,
        "characterId": "yu",
        "icon": "https://apiip.dasewasia.my.id/iconCharacter/chara-yu.png",
        "name": "鈴村優"
      },
      "text": "「私が手伝えることならなんでもするわよ」とも",
      "isChoice": false,
      "stamp": null,
      "image": null,
      "voiceUrl": "https://apiip.dasewasia.my.id/cardStoryVoice/adv_card_yu_51_01/sud_vo_adv_card_yu_51_01-yu026.m4a"
    },
    {
      "id": "msg_95",
      "speaker": {
        "isPlayer": false,
        "characterId": "rui",
        "icon": "https://apiip.dasewasia.my.id/iconCharacter/chara-rui.png",
        "name": "天動瑠依"
      },
      "text": "え、ええ……？",
      "isChoice": false,
      "stamp": null,
      "image": null,
      "voiceUrl": "https://apiip.dasewasia.my.id/cardStoryVoice/adv_card_yu_51_01/sud_vo_adv_card_yu_51_01-rui011.m4a"
    },
    {
      "id": "msg_96",
      "speaker": {
        "isPlayer": false,
        "characterId": "rui",
        "icon": "https://apiip.dasewasia.my.id/iconCharacter/chara-rui.png",
        "name": "天動瑠依"
      },
      "text": "言ったような……言ってないような……",
      "isChoice": false,
      "stamp": null,
      "image": null,
      "voiceUrl": "https://apiip.dasewasia.my.id/cardStoryVoice/adv_card_yu_51_01/sud_vo_adv_card_yu_51_01-rui011.m4a"
    },
    {
      "id": "msg_97",
      "speaker": {
        "isPlayer": false,
        "characterId": "yu",
        "icon": "https://apiip.dasewasia.my.id/iconCharacter/chara-yu.png",
        "name": "鈴村優"
      },
      "text": "言いました！　それと……",
      "isChoice": false,
      "stamp": null,
      "image": null,
      "voiceUrl": "https://apiip.dasewasia.my.id/cardStoryVoice/adv_card_yu_51_01/sud_vo_adv_card_yu_51_01-yu027.m4a"
    },
    {
      "id": "msg_98",
      "speaker": {
        "isPlayer": false,
        "characterId": "yu",
        "icon": "https://apiip.dasewasia.my.id/iconCharacter/chara-yu.png",
        "name": "鈴村優"
      },
      "text": "沙季ちゃんにも協力してほしいんやけど、ええやろか？",
      "isChoice": false,
      "stamp": null,
      "image": null,
      "voiceUrl": "https://apiip.dasewasia.my.id/cardStoryVoice/adv_card_yu_51_01/sud_vo_adv_card_yu_51_01-yu027.m4a"
    },
    {
      "id": "msg_99",
      "speaker": {
        "isPlayer": false,
        "characterId": "ski",
        "icon": "https://apiip.dasewasia.my.id/iconCharacter/chara-saki.png",
        "name": "白石沙季"
      },
      "text": "私に出来ることでしたらもちろんです",
      "isChoice": false,
      "stamp": null,
      "image": null,
      "voiceUrl": "https://apiip.dasewasia.my.id/cardStoryVoice/adv_card_yu_51_01/sud_vo_adv_card_yu_51_01-ski014.m4a"
    },
    {
      "id": "msg_100",
      "speaker": {
        "isPlayer": false,
        "characterId": "ski",
        "icon": "https://apiip.dasewasia.my.id/iconCharacter/chara-saki.png",
        "name": "白石沙季"
      },
      "text": "優ちゃんのお誕生日をお祝いさせて下さい！",
      "isChoice": false,
      "stamp": null,
      "image": null,
      "voiceUrl": "https://apiip.dasewasia.my.id/cardStoryVoice/adv_card_yu_51_01/sud_vo_adv_card_yu_51_01-ski014.m4a"
    },
    {
      "id": "msg_101",
      "speaker": {
        "isPlayer": false,
        "characterId": "yu",
        "icon": "https://apiip.dasewasia.my.id/iconCharacter/chara-yu.png",
        "name": "鈴村優"
      },
      "text": "ありがとう！　じゃあ……二人の一日をうちに下さい！",
      "isChoice": false,
      "stamp": null,
      "image": null,
      "voiceUrl": "https://apiip.dasewasia.my.id/cardStoryVoice/adv_card_yu_51_01/sud_vo_adv_card_yu_51_01-yu028.m4a"
    },
    {
      "id": "msg_102",
      "speaker": {
        "isPlayer": false,
        "characterId": "yu",
        "icon": "https://apiip.dasewasia.my.id/iconCharacter/chara-yu.png",
        "name": "鈴村優"
      },
      "text": "うちと一緒に……オタ活してくれませんか？",
      "isChoice": false,
      "stamp": null,
      "image": null,
      "voiceUrl": "https://apiip.dasewasia.my.id/cardStoryVoice/adv_card_yu_51_01/sud_vo_adv_card_yu_51_01-yu028.m4a"
    }
  ]
}